<?xml version="1.0" encoding="GB2312"?>
<gui>
	<dialog id="20" name="SecPasswordDlg" style="1" caption="keyboard" rect="0,0,0,0" colortopleft="255,98,138,206" colortopright="255,54,105,192" colorbottomleft="255,54,105,192" colorbottomright="255,10,73,179" align="0" showsoundindex="0" hidesoundindex="0"> 
		
	<script>
		function OnGuiEvent(nEvent,nID,pControl) 
			return false 
		end
	</script>
		<controls>
			
		<item id="10" type="Image" style="2" rect="0,0,0,0"  isdefault="0" color="255,255,255,255" textcolor="255,255,255,255" backgroud="1" pack="data\login.gl" group="9" frame="126">		
		</item>
		
		<!--number:0~9-->
		<item id="1" type="Button" style="0" rect="37,87,70,29" isdefault="1" pack="data\login.gl" group="9" frame="0" bitmapbutton="1" framenum="3" />
		<item id="2" type="Button" style="0" rect="88,87,70,29" isdefault="0" pack="data\login.gl" group="9" frame="3" bitmapbutton="1" framenum="3" />
		<item id="3" type="Button" style="0" rect="139,87,70,29" isdefault="0" pack="data\login.gl" group="9" frame="6" bitmapbutton="1" framenum="3" />
		<item id="4" type="Button" style="0" rect="37,129,70,29" isdefault="0" pack="data\login.gl" group="9" frame="9" bitmapbutton="1" framenum="3" />
		<item id="5" type="Button" style="0" rect="88,129,70,29" isdefault="0" pack="data\login.gl" group="9" frame="12" bitmapbutton="1" framenum="3" />
		<item id="6" type="Button" style="0" rect="139,129,70,29" isdefault="0" pack="data\login.gl" group="9" frame="15" bitmapbutton="1" framenum="3" />
		<item id="7" type="Button" style="0" rect="37,171,70,29" isdefault="0" pack="data\login.gl" group="9" frame="18" bitmapbutton="1" framenum="3" />
		<item id="8" type="Button" style="0" rect="88,171,70,29" isdefault="0" pack="data\login.gl" group="9" frame="21" bitmapbutton="1" framenum="3" />
		<item id="9" type="Button" style="0" rect="139,171,70,29" isdefault="0" pack="data\login.gl" group="9" frame="24" bitmapbutton="1" framenum="3" />
		<item id="0" type="Button" style="0" rect="88,212,70,29" isdefault="0" pack="data\login.gl" group="9" frame="27" bitmapbutton="1" framenum="3" />
			 
        <!--"back"--> 		
		<item id="11" type="Button" style="0" rect="32,210,0,0" isdefault="0" pack="data\login.gl" group="9" frame="123" bitmapbutton="1" framenum="3" />
				
		<!--enter-->
		<item id="12" type="Button" style="0" rect="113,210,0,0" isdefault="0" pack="data\login.gl" group="9" frame="120" bitmapbutton="1" framenum="3" />
		<!--display password-->
		<item id="13" type="Static" style="0"  hotkey="0" isdefault="0" color="255,255,255,255" textcolor="255,0,255,0" rect="40,57,130,18"></item>
		
		</controls>
	</dialog>
</gui>
